[
  {
    "id": "brasil-x-tunisia",
    "league": "Internacional - Seleções",
    "homeTeam": "Brasil",
    "awayTeam": "Tunísia",
    "date": "2025-11-18",
    "time": "16:30",
    "timezone": "BRT (Horário de Brasília)",
    "prediction": "Handicap Asiático: Brasil -1.5",
    "hit": false,
    "reason": "Placar: 1 x 1"
  },
  {
    "id": "espanha-x-turquia",
    "league": "Internacional - Seleções",
    "homeTeam": "Espanha",
    "awayTeam": "Turquia",
    "date": "2025-11-18",
    "time": "16:45",
    "timezone": "GMT",
    "prediction": "Total de Gols: Mais de 2.5",
    "hit": true,
    "reason": "Placar: 2 x 2"
  }
]
