[
  {
    "id": "houston-texans-x-buffalo-bills",
    "league": "NFL",
    "country": "Estados Unidos",
    "date": "2025-11-20",
    "time": "22:15",
    "timezone": "UTC",
    "homeTeam": "Houston Texans",
    "awayTeam": "Buffalo Bills",
    "prediction": "Resultado Final: Buffalo Bills",
    "confidence": 63,
    "status": "pending",
    "analysis": "Bills com ataque eficiente em situações de passe e bom aproveitamento em terceira descida; Texans enfrentam dificuldades em proteção e consistência defensiva contra play-action. Matchup favorece Buffalo pela superioridade em skill positions e especial teams." ,
    "hit": false,
    "reason": "Placar: 23 x 19"
  }
]
