[
  {
    "id": "qarabag-x-eintracht-frankfurt",
    "league": "Europa - Champions League",
    "homeTeam": "Qarabag",
    "awayTeam": "Eintracht Frankfurt",
    "date": "2026-01-21",
    "time": "14:45",
    "timezone": "UTC",
    "prediction": "Resultado Final: Eintracht Frankfurt",
    "confidence": 76,
    "status": "pending",
    "analysis": "Frankfurt com mais experiência europeia e melhor transição ofensiva; Qarabag competitivo em casa, mas inferior tecnicamente."
  },
  {
    "id": "galatasaray-x-atletico-madrid",
    "league": "Europa - Champions League",
    "homeTeam": "Galatasaray",
    "awayTeam": "Atletico Madrid",
    "date": "2026-01-21",
    "time": "14:45",
    "timezone": "UTC",
    "prediction": "Ambas as Equipes Marcam: Sim (BTTS)",
    "confidence": 78,
    "status": "pending",
    "analysis": "Ambiente pesado em Istambul e Gala ofensivo; Atlético com qualidade nas transições. Jogo tende a ter gols dos dois lados."
  },
  {
    "id": "atalanta-x-athletic-bilbao",
    "league": "Europa - Champions League",
    "homeTeam": "Atalanta",
    "awayTeam": "Athletic Bilbao",
    "date": "2026-01-21",
    "time": "17:00",
    "timezone": "UTC",
    "prediction": "Total de Gols: Mais de 2.5",
    "confidence": 83,
    "status": "pending",
    "analysis": "Atalanta com ataque de alto volume; Bilbao competitivo e eficiente em bolas paradas. Ritmo indica jogo com 3+ gols."
  },
  {
    "id": "slavia-praga-x-barcelona",
    "league": "Europa - Champions League",
    "homeTeam": "Slavia Praga",
    "awayTeam": "Barcelona",
    "date": "2026-01-21",
    "time": "17:00",
    "timezone": "UTC",
    "prediction": "Resultado Final: Barcelona",
    "confidence": 82,
    "status": "pending",
    "analysis": "Barça com circulação rápida e superioridade técnica; Slavia é intenso, mas tende a sofrer contra posse alta."
  },
  {
    "id": "bayern-munich-x-royale-union-sg",
    "league": "Europa - Champions League",
    "homeTeam": "Bayern Munich",
    "awayTeam": "Royale Union SG",
    "date": "2026-01-21",
    "time": "17:00",
    "timezone": "UTC",
    "prediction": "Bayern Munich vence o 1º Tempo",
    "confidence": 86,
    "status": "pending",
    "analysis": "Bayern com pressão inicial e alto volume ofensivo; Union competitivo, mas deve ceder vantagem ainda na primeira etapa."
  },
  {
    "id": "olympique-marseille-x-liverpool",
    "league": "Europa - Champions League",
    "homeTeam": "Olympique Marseille",
    "awayTeam": "Liverpool",
    "date": "2026-01-21",
    "time": "17:00",
    "timezone": "UTC",
    "prediction": "Ambas as Equipes Marcam: Sim (BTTS)",
    "confidence": 80,
    "status": "pending",
    "analysis": "OM empurra em casa e deixa espaços; Liverpool com ataque muito móvel. Cenário clássico para BTTS."
  },
  {
    "id": "newcastle-x-psv-eindhoven",
    "league": "Europa - Champions League",
    "homeTeam": "Newcastle",
    "awayTeam": "PSV Eindhoven",
    "date": "2026-01-21",
    "time": "17:00",
    "timezone": "UTC",
    "prediction": "Total de Gols: Mais de 2.5",
    "confidence": 82,
    "status": "pending",
    "analysis": "Newcastle agressivo em casa; PSV com ataque veloz e vulnerável atrás. Ritmo alto favorece over 2.5."
  },
  {
    "id": "chelsea-x-pafos",
    "league": "Europa - Champions League",
    "homeTeam": "Chelsea",
    "awayTeam": "Pafos",
    "date": "2026-01-21",
    "time": "17:00",
    "timezone": "UTC",
    "prediction": "Resultado Final: Chelsea",
    "confidence": 85,
    "status": "pending",
    "analysis": "Diferença técnica e física muito grande; Chelsea deve controlar o jogo e vencer sem recorrer a handicap."
  },
  {
    "id": "juventus-x-benfica",
    "league": "Europa - Champions League",
    "homeTeam": "Juventus",
    "awayTeam": "Benfica",
    "date": "2026-01-21",
    "time": "17:00",
    "timezone": "UTC",
    "prediction": "Empate Anula Aposta: Juventus (DNB)",
    "confidence": 74,
    "status": "pending",
    "analysis": "Partida de alto nível e margens pequenas; Juve forte em casa. DNB reduz variância num confronto equilibrado."
  }
]

